crodump/Database.py
crodump/Datafile.py
crodump/Datamodel.py
crodump/__init__.py
crodump/croconvert.py
crodump/crodump.py
crodump/dumpdbfields.py
crodump/hexdump.py
crodump/koddecoder.py
crodump/kodump.py
crodump/readers.py
cronodump-1.1.0.dist-info/LICENSE
cronodump-1.1.0.dist-info/METADATA
cronodump-1.1.0.dist-info/WHEEL
cronodump-1.1.0.dist-info/entry_points.txt
cronodump-1.1.0.dist-info/top_level.txt
cronodump-1.1.0.dist-info/RECORD
