Metadata-Version: 2.1
Name: cronodump
Version: 1.1.0
Summary: Tool and library for extracting data from Cronos databases.
Home-page: https://github.com/alephdata/cronodump/
Author: Willem Hengeveld, Dirk Engling
Author-email: itsme@xs4all.nl, erdgeist@erdgeist.org
License: MIT
Keywords: cronos dataconversion databaseexport
Platform: UNKNOWN
Classifier: Environment :: Console
Classifier: Intended Audience :: End Users/Desktop
Classifier: Intended Audience :: Developers
Classifier: License :: OSI Approved :: MIT License
Classifier: Operating System :: OS Independent
Classifier: Programming Language :: Python :: 3.7
Classifier: Topic :: Utilities
Classifier: Topic :: Database
Requires-Python: >=3.7
Provides-Extra: templates
